odoo/addons/somenergia/__init__.py
odoo/addons/somenergia/__manifest__.py
odoo/addons/somenergia/controllers/__init__.py
odoo/addons/somenergia/controllers/hr_recruitment_main.py
odoo/addons/somenergia/data/config_data.xml
odoo/addons/somenergia/data/hr_leave_data.xml
odoo/addons/somenergia/data/hr_website_recruitment_data.xml
odoo/addons/somenergia/data/leave_type.xml
odoo/addons/somenergia/data/resource_data.xml
odoo/addons/somenergia/demo/hr_leave_demo.xml
odoo/addons/somenergia/i18n/ca_ES.po
odoo/addons/somenergia/i18n/en_US.po
odoo/addons/somenergia/i18n/es.po
odoo/addons/somenergia/i18n_extra/ca_ES.po
odoo/addons/somenergia/i18n_extra/es.po
odoo/addons/somenergia/models/__init__.py
odoo/addons/somenergia/models/account_invoice.py
odoo/addons/somenergia/models/account_invoice_import.py
odoo/addons/somenergia/models/account_journal.py
odoo/addons/somenergia/models/business_document_import.py
odoo/addons/somenergia/models/hr_applicant.py
odoo/addons/somenergia/models/hr_attendance.py
odoo/addons/somenergia/models/hr_employee.py
odoo/addons/somenergia/models/hr_leave.py
odoo/addons/somenergia/models/res_partner_bank.py
odoo/addons/somenergia/static/src/js/greeting_message.js
odoo/addons/somenergia/tests/__init__.py
odoo/addons/somenergia/tests/test_avuinovinc.py
odoo/addons/somenergia/views/account_asset_profile.xml
odoo/addons/somenergia/views/assets.xml
odoo/addons/somenergia/views/hidden_menus.xml
odoo/addons/somenergia/views/hr_attendance_theoretical_time_report.xml
odoo/addons/somenergia/views/hr_attendance_view.xml
odoo/addons/somenergia/views/hr_employee_view.xml
odoo/addons/somenergia/views/hr_leave_view.xml
odoo/addons/somenergia/views/hr_recruitment_views.xml
odoo/addons/somenergia/views/website_hr_recruitment_templates.xml
odoo/addons/somenergia/wizzard/__init__.py
odoo/addons/somenergia/wizzard/hr_attendance_absence.py
odoo12_addon_somenergia-12.0.0.0.16.dist-info/METADATA
odoo12_addon_somenergia-12.0.0.0.16.dist-info/WHEEL
odoo12_addon_somenergia-12.0.0.0.16.dist-info/top_level.txt
odoo12_addon_somenergia-12.0.0.0.16.dist-info/RECORD
