Metadata-Version: 2.1
Name: odoo12-addon-somenergia
Version: 12.0.0.0.16
Summary: Odoo Som Energia customizations
Home-page: https://coopdevs.org
Author: Coopdevs Treball SCCL
License: AGPL-3
Classifier: Programming Language :: Python
Classifier: Framework :: Odoo
Classifier: Framework :: Odoo :: 12.0
Classifier: License :: OSI Approved :: GNU Affero General Public License v3
Requires-Python: >=3.5
Requires-Dist: odoo12-addon-account-asset-management
Requires-Dist: odoo12-addon-account-invoice-import
Requires-Dist: odoo12-addon-account-invoice-import-facturae
Requires-Dist: odoo12-addon-hr-attendance-report-theoretical-time
Requires-Dist: odoo12-addon-hr-employee-multidepartment
Requires-Dist: odoo (<12.1dev,>=12.0a)
